pytreex/__init__.py
pytreex/pytree.py
pytreex/types.py
pytreex/utils.py
pytreex-0.0.1.dist-info/LICENSE
pytreex-0.0.1.dist-info/WHEEL
pytreex-0.0.1.dist-info/METADATA
pytreex-0.0.1.dist-info/RECORD
