Metadata-Version: 2.1
Name: pytreex
Version: 0.0.1
Summary: 
Author: Cristian Garcia
Author-email: cgarcia.e88@gmail.com
Requires-Python: >=3.7,<4.0
Classifier: Programming Language :: Python :: 3
Classifier: Programming Language :: Python :: 3.7
Classifier: Programming Language :: Python :: 3.8
Classifier: Programming Language :: Python :: 3.9
Requires-Dist: jax (>=0.2.18,<0.3.0)
Requires-Dist: jaxlib (>=0.1.70,<0.2.0)
